shoji/__init__.py
shoji/bam_parser.py
shoji/chrom_interval.py
shoji/cli.py
shoji/count.py
shoji/create_matrix.py
shoji/create_sliding_windows.py
shoji/gene.py
shoji/gff3_parser.py
shoji/helpers.py
shoji/interval.py
shoji/map_to_id.py
shoji/output.py
shoji/pyarrow_reader.py
shoji/schemas.py
shoji/tabix_converter.py
shoji/tree.py
shoji-0.41.2.dist-info/LICENSE
shoji-0.41.2.dist-info/METADATA
shoji-0.41.2.dist-info/WHEEL
shoji-0.41.2.dist-info/entry_points.txt
shoji-0.41.2.dist-info/RECORD
