Metadata-Version: 2.3
Name: shoji
Version: 0.41.2
Summary: post process *clip reads after alignment. Replacement for htseq-clip
License: MIT
Author: Sudeep Sahadevan
Requires-Python: >=3.11,<4.0
Classifier: License :: OSI Approved :: MIT License
Classifier: Programming Language :: Python :: 3
Classifier: Programming Language :: Python :: 3.11
Classifier: Programming Language :: Python :: 3.12
Classifier: Programming Language :: Python :: 3.13
Requires-Dist: cython (>=3.0.10,<4.0.0)
Requires-Dist: loguru (>=0.7.2,<0.8.0)
Requires-Dist: numpy (>=1.26.4,<2.0.0)
Requires-Dist: pyarrow (>=20.0.0,<21.0.0)
Requires-Dist: pysam (>=0.23.3,<0.24.0)
Requires-Dist: rich-click (>=1.8.3,<2.0.0)
Requires-Dist: sortedcontainers (>=2.4.0,<3.0.0)
Project-URL: Documentation, https://shoji.readthedocs.io/
Project-URL: Homepage, https://github.com/EMBL-Hentze-group/Shoji/
